seclook/__init__.py
seclook/cli.py
seclook/config_helper.py
seclook/find_config.py
seclook/lookups/__init__.py
seclook/lookups/abuseipdb_lookup.py
seclook/lookups/emailrep_lookup.py
seclook/lookups/greynoise_lookup.py
seclook/lookups/pulsedive_lookup.py
seclook/lookups/shodan_lookup.py
seclook/lookups/threatfox_lookup.py
seclook/lookups/virustotal_lookup.py
seclook/lookups/yaraify_lookup.py
seclook/openai/__init__.py
seclook/openai/gpt4_summarize.py
seclook/tests/__init__.py
seclook/tests/test_export.py
seclook/tests/test_list.py
seclook/tests/test_missing_service_value.py
seclook/tests/test_missing_value.py
seclook/tests/test_unknown_service.py
seclook/tests/test_valid_service_value.py
seclook-0.7.2.dist-info/LICENSE
seclook-0.7.2.dist-info/METADATA
seclook-0.7.2.dist-info/WHEEL
seclook-0.7.2.dist-info/entry_points.txt
seclook-0.7.2.dist-info/RECORD
