Metadata-Version: 2.1
Name: seclook
Version: 0.7.2
Summary: Simple security lookups via CLI
Home-page: https://github.com/ackatz/seclook-cli
License: MIT
Author: ackatz
Author-email: andrew@akatz.org
Requires-Python: >=3.11,<4.0
Classifier: License :: OSI Approved :: MIT License
Classifier: Programming Language :: Python :: 3
Classifier: Programming Language :: Python :: 3.11
Classifier: Programming Language :: Python :: 3.12
Requires-Dist: click (>=8.1.7,<9.0.0)
Requires-Dist: configparser (>=6.0.0,<7.0.0)
Requires-Dist: requests (>=2.31.0,<3.0.0)
